rfc7539/__init__.py
rfc7539/_chacha20.cpython-35m-darwin.so
rfc7539/_poly1305.cpython-35m-darwin.so
rfc7539/aead.py
rfc7539/cipher.py
rfc7539/mac.py
rfc7539/test.py
rfc7539-2.0.1.dist-info/LICENSE
rfc7539-2.0.1.dist-info/METADATA
rfc7539-2.0.1.dist-info/WHEEL
rfc7539-2.0.1.dist-info/top_level.txt
rfc7539-2.0.1.dist-info/RECORD
