Metadata-Version: 1.1
Name: rfc7539
Version: 2.0.1
Summary: An AEAD construction per RFC7539
Home-page: https://github.com/AntonKueltz/rfc7539
Author: Anton Kueltz
Author-email: kueltz.anton@gmail.com
License: GNU General Public License v3 (GPLv3)
Keywords: rfc7539 poly1305 chacha20 chacha20poly1305
Platform: UNKNOWN
Classifier: Development Status :: 4 - Beta
Classifier: Intended Audience :: Developers
Classifier: Topic :: Security :: Cryptography
Classifier: Operating System :: POSIX :: Linux
Classifier: Operating System :: MacOS :: MacOS X
Classifier: License :: OSI Approved :: GNU General Public License v3 (GPLv3)
Classifier: Programming Language :: Python :: 3.5
Classifier: Programming Language :: Python :: 3.6
Classifier: Programming Language :: Python :: 3.7
Classifier: Programming Language :: Python :: 3.8
